cellpose_quantification/__init__.py
cellpose_quantification/cli.py
cellpose_quantification/quantification.py
tests/test_cli.py
tests/test_integration.py
tests/test_quantification.py
cellpose_quantification-0.3.0.dist-info/METADATA
cellpose_quantification-0.3.0.dist-info/WHEEL
cellpose_quantification-0.3.0.dist-info/entry_points.txt
cellpose_quantification-0.3.0.dist-info/top_level.txt
cellpose_quantification-0.3.0.dist-info/RECORD
